Workbook
Name Slicer_Region: #N/A

Sheet Product Master
A1: Product ID | B1: Product Name | C1: Category | D1: Unit Price | E1: Cost Price
A2: P101 | B2: Laptop | C2: Electronics | D2: 50000 | E2: 42000
A3: P102 | B3: Mouse | C3: Electronics | D3: 800 | E3: 500
A4: P103 | B4: Keyboard | C4: Electronics | D4: 1200 | E4: 850
A5: P104 | B5: Monitor | C5: Electronics | D5: 15000 | E5: 12500
A6: P105 | B6: Printer | C6: Electronics | D6: 9000 | E6: 7600
A7: P106 | B7: Mobile | C7: Electronics | D7: 25000 | E7: 21000
A8: P107 | B8: Earbuds | C8: Electronics | D8: 2000 | E8: 1500
A9: P108 | B9: Smart Watch | C9: Electronics | D9: 6000 | E9: 5000
A10: P109 | B10: Chair | C10: Furniture | D10: 3500 | E10: 2800
A11: P110 | B11: Table | C11: Furniture | D11: 7000 | E11: 5800
A12: P111 | B12: Sofa | C12: Furniture | D12: 25000 | E12: 21000
A13: P112 | B13: Cupboard | C13: Furniture | D13: 18000 | E13: 15000
... A31: P130 | B31: Mouse Pad | C31: Accessories | D31: 250 | E31: 150

Sheet Customer_Master
A1: Customer ID | B1: Customer Name | C1: Region | D1: State
A2: C001 | B2: Amit Patel | C2: West | D2: Gujarat
A3: C002 | B3: Rahul Shah | C3: West | D3: Gujarat
A4: C003 | B4: Neha Patel | C4: West | D4: Gujarat
A5: C004 | B5: Priya Mehta | C5: West | D5: Maharashtra
A6: C005 | B6: Karan Joshi | C6: West | D6: Maharashtra
A7: C006 | B7: Riya Desai | C7: West | D7: Rajasthan
A8: C007 | B8: Mohit Singh | C8: North | D8: Delhi
A9: C008 | B9: Anjali Verma | C9: North | D9: Delhi
A10: C009 | B10: Rohit Kumar | C10: North | D10: Punjab
A11: C010 | B11: Simran Kaur | C11: North | D11: Punjab
A12: C011 | B12: Arjun Sharma | C12: North | D12: Haryana
... A31: C030 | B31: Priti Sharma | C31: East | D31: Bihar

Sheet Sales Data
A1: Order ID | B1: Order Date | C1: Customer ID | D1: Product ID | E1: Quantity | F1: Product Name | G1: Category | H1: Unit Price | I1: Cost Price | J1: Sales | K1: Profit | L1: Customer Name | M1: Region | N1: State
A2: 1001 | B2: 45658 | C2: C001 | D2: P101 | E2: 2 | F2: =VLOOKUP(D2,Table1[#All],2,0) -> Laptop | G2: =VLOOKUP(D2,Table1[#All],3,0) -> Electronics | H2: =VLOOKUP(D2,Table1[#All],4,) -> 50000 | I2: =VLOOKUP(D2,Table1[#All],5,) -> 42000 | J2: =PRODUCT(H2,E2) -> 100000 | K2: =J2-(I2*E2) -> 16000 | L2: =VLOOKUP(C2,Table2[#All],2,) -> Amit Patel | M2: =VLOOKUP(C2,Table2[#All],3,) -> West | N2: =VLOOKUP(C2,Table2[#All],4,) -> Gujarat
A3: 1002 | B3: 45659 | C3: C002 | D3: P102 | E3: 3 | F3: =VLOOKUP(D3,Table1[#All],2,0) -> Mouse | G3: =VLOOKUP(D3,Table1[#All],3,0) -> Electronics | H3: =VLOOKUP(D3,Table1[#All],4,) -> 800 | I3: =VLOOKUP(D3,Table1[#All],5,) -> 500 | J3: =PRODUCT(H3,E3) -> 2400 | K3: =J3-(I3*E3) -> 900 | L3: =VLOOKUP(C3,Table2[#All],2,) -> Rahul Shah | M3: =VLOOKUP(C3,Table2[#All],3,) -> West | N3: =VLOOKUP(C3,Table2[#All],4,) -> Gujarat
A4: 1003 | B4: 45660 | C4: C003 | D4: P103 | E4: 4 | F4: =VLOOKUP(D4,Table1[#All],2,0) -> Keyboard | G4: =VLOOKUP(D4,Table1[#All],3,0) -> Electronics | H4: =VLOOKUP(D4,Table1[#All],4,) -> 1200 | I4: =VLOOKUP(D4,Table1[#All],5,) -> 850 | J4: =PRODUCT(H4,E4) -> 4800 | K4: =J4-(I4*E4) -> 1400 | L4: =VLOOKUP(C4,Table2[#All],2,) -> Neha Patel | M4: =VLOOKUP(C4,Table2[#All],3,) -> West | N4: =VLOOKUP(C4,Table2[#All],4,) -> Gujarat
A5: 1004 | B5: 45661 | C5: C004 | D5: P104 | E5: 1 | F5: =VLOOKUP(D5,Table1[#All],2,0) -> Monitor | G5: =VLOOKUP(D5,Table1[#All],3,0) -> Electronics | H5: =VLOOKUP(D5,Table1[#All],4,) -> 15000 | I5: =VLOOKUP(D5,Table1[#All],5,) -> 12500 | J5: =PRODUCT(H5,E5) -> 15000 | K5: =J5-(I5*E5) -> 2500 | L5: =VLOOKUP(C5,Table2[#All],2,) -> Priya Mehta | M5: =VLOOKUP(C5,Table2[#All],3,) -> West | N5: =VLOOKUP(C5,Table2[#All],4,) -> Maharashtra
A6: 1005 | B6: 45662 | C6: C005 | D6: P105 | E6: 5 | F6: =VLOOKUP(D6,Table1[#All],2,0) -> Printer | G6: =VLOOKUP(D6,Table1[#All],3,0) -> Electronics | H6: =VLOOKUP(D6,Table1[#All],4,) -> 9000 | I6: =VLOOKUP(D6,Table1[#All],5,) -> 7600 | J6: =PRODUCT(H6,E6) -> 45000 | K6: =J6-(I6*E6) -> 7000 | L6: =VLOOKUP(C6,Table2[#All],2,) -> Karan Joshi | M6: =VLOOKUP(C6,Table2[#All],3,) -> West | N6: =VLOOKUP(C6,Table2[#All],4,) -> Maharashtra
A7: 1006 | B7: 45663 | C7: C006 | D7: P106 | E7: 1 | F7: =VLOOKUP(D7,Table1[#All],2,0) -> Mobile | G7: =VLOOKUP(D7,Table1[#All],3,0) -> Electronics | H7: =VLOOKUP(D7,Table1[#All],4,) -> 25000 | I7: =VLOOKUP(D7,Table1[#All],5,) -> 21000 | J7: =PRODUCT(H7,E7) -> 25000 | K7: =J7-(I7*E7) -> 4000 | L7: =VLOOKUP(C7,Table2[#All],2,) -> Riya Desai | M7: =VLOOKUP(C7,Table2[#All],3,) -> West | N7: =VLOOKUP(C7,Table2[#All],4,) -> Rajasthan
A8: 1007 | B8: 45664 | C8: C007 | D8: P107 | E8: 3 | F8: =VLOOKUP(D8,Table1[#All],2,0) -> Earbuds | G8: =VLOOKUP(D8,Table1[#All],3,0) -> Electronics | H8: =VLOOKUP(D8,Table1[#All],4,) -> 2000 | I8: =VLOOKUP(D8,Table1[#All],5,) -> 1500 | J8: =PRODUCT(H8,E8) -> 6000 | K8: =J8-(I8*E8) -> 1500 | L8: =VLOOKUP(C8,Table2[#All],2,) -> Mohit Singh | M8: =VLOOKUP(C8,Table2[#All],3,) -> North | N8: =VLOOKUP(C8,Table2[#All],4,) -> Delhi
A9: 1008 | B9: 45665 | C9: C008 | D9: P108 | E9: 2 | F9: =VLOOKUP(D9,Table1[#All],2,0) -> Smart Watch | G9: =VLOOKUP(D9,Table1[#All],3,0) -> Electronics | H9: =VLOOKUP(D9,Table1[#All],4,) -> 6000 | I9: =VLOOKUP(D9,Table1[#All],5,) -> 5000 | J9: =PRODUCT(H9,E9) -> 12000 | K9: =J9-(I9*E9) -> 2000 | L9: =VLOOKUP(C9,Table2[#All],2,) -> Anjali Verma | M9: =VLOOKUP(C9,Table2[#All],3,) -> North | N9: =VLOOKUP(C9,Table2[#All],4,) -> Delhi
A10: 1009 | B10: 45666 | C10: C009 | D10: P109 | E10: 2 | F10: =VLOOKUP(D10,Table1[#All],2,0) -> Chair | G10: =VLOOKUP(D10,Table1[#All],3,0) -> Furniture | H10: =VLOOKUP(D10,Table1[#All],4,) -> 3500 | I10: =VLOOKUP(D10,Table1[#All],5,) -> 2800 | J10: =PRODUCT(H10,E10) -> 7000 | K10: =J10-(I10*E10) -> 1400 | L10: =VLOOKUP(C10,Table2[#All],2,) -> Rohit Kumar | M10: =VLOOKUP(C10,Table2[#All],3,) -> North | N10: =VLOOKUP(C10,Table2[#All],4,) -> Punjab
A11: 1010 | B11: 45667 | C11: C010 | D11: P110 | E11: 2 | F11: =VLOOKUP(D11,Table1[#All],2,0) -> Table | G11: =VLOOKUP(D11,Table1[#All],3,0) -> Furniture | H11: =VLOOKUP(D11,Table1[#All],4,) -> 7000 | I11: =VLOOKUP(D11,Table1[#All],5,) -> 5800 | J11: =PRODUCT(H11,E11) -> 14000 | K11: =J11-(I11*E11) -> 2400 | L11: =VLOOKUP(C11,Table2[#All],2,) -> Simran Kaur | M11: =VLOOKUP(C11,Table2[#All],3,) -> North | N11: =VLOOKUP(C11,Table2[#All],4,) -> Punjab
A12: 1011 | B12: 45668 | C12: C011 | D12: P111 | E12: 4 | F12: =VLOOKUP(D12,Table1[#All],2,0) -> Sofa | G12: =VLOOKUP(D12,Table1[#All],3,0) -> Furniture | H12: =VLOOKUP(D12,Table1[#All],4,) -> 25000 | I12: =VLOOKUP(D12,Table1[#All],5,) -> 21000 | J12: =PRODUCT(H12,E12) -> 100000 | K12: =J12-(I12*E12) -> 16000 | L12: =VLOOKUP(C12,Table2[#All],2,) -> Arjun Sharma | M12: =VLOOKUP(C12,Table2[#All],3,) -> North | N12: =VLOOKUP(C12,Table2[#All],4,) -> Haryana
A13: 1012 | B13: 45669 | C13: C012 | D13: P112 | E13: 2 | F13: =VLOOKUP(D13,Table1[#All],2,0) -> Cupboard | G13: =VLOOKUP(D13,Table1[#All],3,0) -> Furniture | H13: =VLOOKUP(D13,Table1[#All],4,) -> 18000 | I13: =VLOOKUP(D13,Table1[#All],5,) -> 15000 | J13: =PRODUCT(H13,E13) -> 36000 | K13: =J13-(I13*E13) -> 6000 | L13: =VLOOKUP(C13,Table2[#All],2,) -> Sneha Gupta | M13: =VLOOKUP(C13,Table2[#All],3,) -> North | N13: =VLOOKUP(C13,Table2[#All],4,) -> Uttar Pradesh
... A101: 1100 | B101: 45757 | C101: C010 | D101: P110 | E101: 4 | F101: =VLOOKUP(D101,Table1[#All],2,0) -> Table | G101: =VLOOKUP(D101,Table1[#All],3,0) -> Furniture | H101: =VLOOKUP(D101,Table1[#All],4,) -> 7000 | I101: =VLOOKUP(D101,Table1[#All],5,) -> 5800 | J101: =PRODUCT(H101,E101) -> 28000 | K101: =J101-(I101*E101) -> 4800 | L101: =VLOOKUP(C101,Table2[#All],2,) -> Simran Kaur | M101: =VLOOKUP(C101,Table2[#All],3,) -> North | N101: =VLOOKUP(C101,Table2[#All],4,) -> Punjab

Sheet Analysis
A1: Retail Sales Analysis
A3: KPI Summary | E3: Pivot Table Analysis
A5: Total Sales | B5: =SUM('Sales Data'!J2:J101) -> 2459740 | F5: Category | G5: Sum of Sales | I5: Category | J5: Sum of Profit | L5: State | M5: Sum of Sales
A6: Total Profit | B6: =SUM('Sales Data'!K2:K101) -> 413135 | F6: Accessories | G6: 23250 | I6: Accessories | J6: 7250 | L6: Bihar | M6: 2480
A7: Average Sales | B7: =AVERAGE('Sales Data'!J2:J101) -> 24597.4 | F7: Electronics | G7: 1350850 | I7: Electronics | J7: 225300 | L7: Delhi | M7: 92000
A8: Median Sales | B8: =MEDIAN('Sales Data'!J2:J101) -> 6000 | F8: Furniture | G8: 1055300 | I8: Furniture | J8: 173000 | L8: Gujarat | M8: 717000
A9: Total Orders | B9: =COUNTA('Sales Data'!A2:A101) -> 100 | F9: Stationery | G9: 30340 | I9: Stationery | J9: 7585 | L9: Haryana | M9: 303150
A10: Total Quantity | B10: =SUM('Sales Data'!E2:E101) -> 285 | F10: Grand Total | G10: 2459740 | I10: Grand Total | J10: 413135 | L10: Karnataka | M10: 5600
A11: Average Profit | B11: =AVERAGE('Sales Data'!K2:K101) -> 4131.35 | L11: Kerala | M11: 25800
L12: Maharashtra | M12: 336000
L13: Odisha | M13: 11340
A14: Formula Practice | L14: Punjab | M14: 161000
B15: Result | L15: Rajasthan | M15: 278750
A16: IF | B16: =IF(B5>2000000,"Target Achieved","Target not Achieved") -> Target Achieved | L16: Tamil Nadu | M16: 26100
A17: SUMIF | B17: =SUMIF('Sales Data'!G2:G101,"Electronics",'Sales Data'!J2:J1010) -> 1350850 | C17: Electronic Total Sales | L17: Telangana | M17: 2000
A18: MATCH | B18: =MATCH("P110",Table1[Product ID],) -> 10 | C18: Position of Product ID P110 | L18: Uttar Pradesh | M18: 498000
A19: INDEX | B19: {=INDEX(Table1[Product Name],10,0)} -> Table | L19: West Bengal | M19: 520
L20: Grand Total | M20: 2459740

Sheet Dashboard
A1: Retail Sales Dashboard
A4: Total Sales | B4: Total Profit | C4: Total Orders | D4: Average Sales
A5: =Analysis!B5 -> 2459740 | B5: =Analysis!B6 -> 413135 | C5: =Analysis!B9 -> 100 | D5: =Analysis!B7 -> 24597.4
